Workbook

Sheet Tarifario
A1: Segmento Copa | B1: Concessionaria | C1: Preço da Concessionaria é: | D1: Classe | E1: UF | F1: Concessionária | G1: Segmento | H1: Faixa Mín (m3) | I1: Faixa Máx (m3) | J1: Tarifa (R$/m³) | K1: Termo Fixo (R$) | L1: dt_delib | M1: PIS/Cofins | N1: ICMS | O1: Ordem | P1: Tabela | Q1: Tarifa em cascata? | R1: Fonte | S1: Periodo de renovação
A2: CONDOMINIOS | B2: SP (Comgás) | C2: com pis/cofins e sem icms | D2: 1 | E2: SP | F2: COMGÁS | G2: Residencial - Medição Coletiva | H2: 0 | I2: 500 | J2: 7.732893 | K2: 78.14 | L2: 46182 | M2: 0.089 | N2: =_xlfn.XLOOKUP(E2,ICMS!C:C,ICMS!D:D) -> 0.15 | O2: 1 | Q2: Não | R2: https://www.comgas.com.br/sobre-sua-conta/tarifas | S2: março, junho, setembro, dezembro
A3: CONDOMINIOS | B3: SP (Comgás) | C3: com pis/cofins e sem icms | D3: 2 | E3: SP | F3: COMGÁS | G3: Residencial - Medição Coletiva | H3: =I2+0.01 -> 500.01 | I3: 2000 | J3: 7.51779 | K3: 186.85 | L3: 46182 | M3: 0.089 | N3: =_xlfn.XLOOKUP(E3,ICMS!C:C,ICMS!D:D) -> 0.15 | O3: =1+O2 -> 2 | Q3: Não | R3: https://www.comgas.com.br/sobre-sua-conta/tarifas | S3: março, junho, setembro, dezembro
A4: CONDOMINIOS | B4: SP (Comgás) | C4: com pis/cofins e sem icms | D4: 3 | E4: SP | F4: COMGÁS | G4: Residencial - Medição Coletiva | H4: =I3+0.01 -> 2000.01 | I4: 99999999999 | J4: 7.248912 | K4: 730.35 | L4: 46182 | M4: 0.089 | N4: =_xlfn.XLOOKUP(E4,ICMS!C:C,ICMS!D:D) -> 0.15 | O4: =1+O3 -> 3 | Q4: Não | R4: https://www.comgas.com.br/sobre-sua-conta/tarifas | S4: março, junho, setembro, dezembro
A5: COMERCIAL E SERVIÇOS | B5: SP (Comgás) | C5: com pis/cofins e sem icms | D5: 1 | E5: SP | F5: COMGÁS | G5: Comercial | H5: 0 | I5: 150 | J5: 7.36581 | K5: 53.29 | L5: 46182 | M5: 0.089 | N5: =_xlfn.XLOOKUP(E5,ICMS!C:C,ICMS!D:D) -> 0.15 | O5: =1+O4 -> 4 | Q5: Não | R5: https://www.comgas.com.br/sobre-sua-conta/tarifas | S5: março, junho, setembro, dezembro
A6: COMERCIAL E SERVIÇOS | B6: SP (Comgás) | C6: com pis/cofins e sem icms | D6: 2 | E6: SP | F6: COMGÁS | G6: Comercial | H6: =I5+0.01 -> 150.01 | I6: 500 | J6: 6.929245 | K6: 119.47 | L6: 46182 | M6: 0.089 | N6: =_xlfn.XLOOKUP(E6,ICMS!C:C,ICMS!D:D) -> 0.15 | O6: =1+O5 -> 5 | Q6: Não | R6: https://www.comgas.com.br/sobre-sua-conta/tarifas | S6: março, junho, setembro, dezembro
A7: COMERCIAL E SERVIÇOS | B7: SP (Comgás) | C7: com pis/cofins e sem icms | D7: 3 | E7: SP | F7: COMGÁS | G7: Comercial | H7: =I6+0.01 -> 500.01 | I7: 3500 | J7: 6.293442 | K7: 440.78 | L7: 46182 | M7: 0.089 | N7: =_xlfn.XLOOKUP(E7,ICMS!C:C,ICMS!D:D) -> 0.15 | O7: =1+O6 -> 6 | Q7: Não | R7: https://www.comgas.com.br/sobre-sua-conta/tarifas | S7: março, junho, setembro, dezembro
A8: COMERCIAL E SERVIÇOS | B8: SP (Comgás) | C8: com pis/cofins e sem icms | D8: 4 | E8: SP | F8: COMGÁS | G8: Comercial | H8: =I7+0.01 -> 3500.01 | I8: 50000 | J8: 5.002828 | K8: 5006.35 | L8: 46182 | M8: 0.089 | N8: =_xlfn.XLOOKUP(E8,ICMS!C:C,ICMS!D:D) -> 0.15 | O8: =1+O7 -> 7 | Q8: Não | R8: https://www.comgas.com.br/sobre-sua-conta/tarifas | S8: março, junho, setembro, dezembro
A9: COMERCIAL E SERVIÇOS | B9: SP (Comgás) | C9: com pis/cofins e sem icms | D9: 5 | E9: SP | F9: COMGÁS | G9: Comercial | H9: =I8+0.01 -> 50000.01 | I9: 99999999999 | J9: 4.787725 | K9: 15876.35 | L9: 46182 | M9: 0.089 | N9: =_xlfn.XLOOKUP(E9,ICMS!C:C,ICMS!D:D) -> 0.15 | O9: =1+O8 -> 8 | Q9: Não | R9: https://www.comgas.com.br/sobre-sua-conta/tarifas | S9: março, junho, setembro, dezembro
A10: INDUSTRIAL | B10: SP (Comgás) | C10: com pis/cofins e sem icms | D10: 1 | E10: SP | F10: COMGÁS | G10: Industrial e Interruptível | H10: 0 | I10: 50000 | J10: 4.149025 | K10: 299.94 | L10: 46182 | M10: 0.089 | N10: =_xlfn.XLOOKUP(E10,ICMS!C:C,ICMS!D:D) -> 0.15 | O10: =1+O9 -> 9 | Q10: Não | R10: https://www.comgas.com.br/sobre-sua-conta/tarifas | S10: março, junho, setembro, dezembro
A11: INDUSTRIAL | B11: SP (Comgás) | C11: com pis/cofins e sem icms | D11: 2 | E11: SP | F11: COMGÁS | G11: Industrial e Interruptível | H11: =I10+0.01 -> 50000.01 | I11: 300000 | J11: 3.243632 | K11: 45569.61 | L11: 46182 | M11: 0.089 | N11: =_xlfn.XLOOKUP(E11,ICMS!C:C,ICMS!D:D) -> 0.15 | O11: =1+O10 -> 10 | Q11: Não | R11: https://www.comgas.com.br/sobre-sua-conta/tarifas | S11: março, junho, setembro, dezembro
A12: INDUSTRIAL | B12: SP (Comgás) | C12: com pis/cofins e sem icms | D12: 3 | E12: SP | F12: COMGÁS | G12: Industrial e Interruptível | H12: =I11+0.01 -> 300000.01 | I12: 500000 | J12: 3.139563 | K12: 76814.74 | L12: 46182 | M12: 0.089 | N12: =_xlfn.XLOOKUP(E12,ICMS!C:C,ICMS!D:D) -> 0.15 | O12: =1+O11 -> 11 | Q12: Não | R12: https://www.comgas.com.br/sobre-sua-conta/tarifas | S12: março, junho, setembro, dezembro
A13: INDUSTRIAL | B13: SP (Comgás) | C13: com pis/cofins e sem icms | D13: 4 | E13: SP | F13: COMGÁS | G13: Industrial e Interruptível | H13: =I12+0.01 -> 500000.01 | I13: 1000000 | J13: 3.085472 | K13: 104696.61 | L13: 46182 | M13: 0.089 | N13: =_xlfn.XLOOKUP(E13,ICMS!C:C,ICMS!D:D) -> 0.15 | O13: =1+O12 -> 12 | Q13: Não | R13: https://www.comgas.com.br/sobre-sua-conta/tarifas | S13: março, junho, setembro, dezembro
A14: INDUSTRIAL | B14: SP (Comgás) | C14: com pis/cofins e sem icms | D14: 5 | E14: SP | F14: COMGÁS | G14: Industrial e Interruptível | H14: =I13+0.01 -> 1000000 | I14: 2000000 | J14: 3.04572 | K14: 145676.98 | L14: 46182 | M14: 0.089 | N14: =_xlfn.XLOOKUP(E14,ICMS!C:C,ICMS!D:D) -> 0.15 | O14: =1+O13 -> 13 | Q14: Não | R14: https://www.comgas.com.br/sobre-sua-conta/tarifas | S14: março, junho, setembro, dezembro
A15: INDUSTRIAL | B15: SP (Comgás) | C15: com pis/cofins e sem icms | D15: 6 | E15: SP | F15: COMGÁS | G15: Industrial e Interruptível | H15: =I14+0.01 -> 2000000 | I15: 99999999999 | J15: 2.995953 | K15: 248290.96 | L15: 46182 | M15: 0.089 | N15: =_xlfn.XLOOKUP(E15,ICMS!C:C,ICMS!D:D) -> 0.15 | O15: =1+O14 -> 14 | Q15: Não | R15: https://www.comgas.com.br/sobre-sua-conta/tarifas | S15: março, junho, setembro, dezembro
A16: REVENDA | B16: SP (Comgás) | C16: com pis/cofins e sem icms | D16: 1 | E16: SP | F16: COMGÁS | G16: Residencial | H16: 0 | I16: 1 | J16: 2.337387 | K16: 10.54 | L16: 46182 | M16: 0.089 | N16: =_xlfn.XLOOKUP(E16,ICMS!C:C,ICMS!D:D) -> 0.15 | O16: =1+O15 -> 15 | Q16: Não | R16: https://www.comgas.com.br/sobre-sua-conta/tarifas | S16: março, junho, setembro, dezembro
A17: REVENDA | B17: SP (Comgás) | C17: com pis/cofins e sem icms | D17: 2 | E17: SP | F17: COMGÁS | G17: Residencial | H17: =I16+0.01 -> 1.01 | I17: 3 | J17: 11.502461 | K17: 1.38 | L17: 46182 | M17: 0.089 | N17: =_xlfn.XLOOKUP(E17,ICMS!C:C,ICMS!D:D) -> 0.15 | O17: =1+O16 -> 16 | Q17: Não | R17: https://www.comgas.com.br/sobre-sua-conta/tarifas | S17: março, junho, setembro, dezembro
A18: REVENDA | B18: SP (Comgás) | C18: com pis/cofins e sem icms | D18: 3 | E18: SP | F18: COMGÁS | G18: Residencial | H18: =I17+0.01 -> 3.01 | I18: 7 | J18: 4.865142 | K18: 21.3 | L18: 46182 | M18: 0.089 | N18: =_xlfn.XLOOKUP(E18,ICMS!C:C,ICMS!D:D) -> 0.15 | O18: =1+O17 -> 17 | Q18: Não | R18: https://www.comgas.com.br/sobre-sua-conta/tarifas | S18: março, junho, setembro, dezembro
A19: REVENDA | B19: SP (Comgás) | C19: com pis/cofins e sem icms | D19: 4 | E19: SP | F19: COMGÁS | G19: Residencial | H19: =I18+0.01 -> 7.01 | I19: 14 | J19: 8.566749 | K19: -4.63 | L19: 46182 | M19: 0.089 | N19: =_xlfn.XLOOKUP(E19,ICMS!C:C,ICMS!D:D) -> 0.15 | O19: =1+O18 -> 18 | Q19: Não | R19: https://www.comgas.com.br/sobre-sua-conta/tarifas | S19: março, junho, setembro, dezembro
A20: REVENDA | B20: SP (Comgás) | C20: com pis/cofins e sem icms | D20: 5 | E20: SP | F20: COMGÁS | G20: Residencial | H20: =I19+0.01 -> 14.01 | I20: 99999999999 | J20: 10.052583 | K20: -25.43 | L20: 46182 | M20: 0.089 | N20: =_xlfn.XLOOKUP(E20,ICMS!C:C,ICMS!D:D) -> 0.15 | O20: =1+O19 -> 19 | Q20: Não | R20: https://www.comgas.com.br/sobre-sua-conta/tarifas | S20: março, junho, setembro, dezembro
A21: REVENDA | B21: SP (Naturgy) | C21: com pis/cofins e sem icms | D21: 1 | E21: SP | F21: NATURGY | G21: Residencial | H21: 0 | I21: 1 | J21: 1.8863 | K21: 25.29 | L21: 46173 | M21: 0.09 | N21: =_xlfn.XLOOKUP(E21,ICMS!C:C,ICMS!D:D) -> 0.15 | O21: =1+O20 -> 20 | Q21: Não | R21: https://www.naturgy.com.br/atendimento/tarifas/tarifa_sao_paulo | S21: fevereiro, maio,agosto, novembro
A22: REVENDA | B22: SP (Naturgy) | C22: com pis/cofins e sem icms | D22: 2 | E22: SP | F22: NATURGY | G22: Residencial | H22: =I21+0.01 -> 1.01 | I22: 7 | J22: 6.6179 | K22: 19.77 | L22: 46173 | M22: 0.09 | N22: =_xlfn.XLOOKUP(E22,ICMS!C:C,ICMS!D:D) -> 0.15 | O22: =1+O21 -> 21 | Q22: Não | R22: https://www.naturgy.com.br/atendimento/tarifas/tarifa_sao_paulo | S22: fevereiro, maio,agosto, novembro
A23: REVENDA | B23: SP (Naturgy) | C23: com pis/cofins e sem icms | D23: 3 | E23: SP | F23: NATURGY | G23: Residencial | H23: =I22+0.01 -> 7.01 | I23: 16 | J23: 6.425 | K23: 21.32 | L23: 46173 | M23: 0.09 | N23: =_xlfn.XLOOKUP(E23,ICMS!C:C,ICMS!D:D) -> 0.15 | O23: =1+O22 -> 22 | Q23: Não | R23: https://www.naturgy.com.br/atendimento/tarifas/tarifa_sao_paulo | S23: fevereiro, maio,agosto, novembro
A24: REVENDA | B24: SP (Naturgy) | C24: com pis/cofins e sem icms | D24: 4 | E24: SP | F24: NATURGY | G24: Residencial | H24: =I23+0.01 -> 16.01 | I24: 41 | J24: 6.2942 | K24: 23.75 | L24: 46173 | M24: 0.09 | N24: =_xlfn.XLOOKUP(E24,ICMS!C:C,ICMS!D:D) -> 0.15 | O24: =1+O23 -> 23 | Q24: Não | R24: https://www.naturgy.com.br/atendimento/tarifas/tarifa_sao_paulo | S24: fevereiro, maio,agosto, novembro
A25: REVENDA | B25: SP (Naturgy) | C25: com pis/cofins e sem icms | D25: 5 | E25: SP | F25: NATURGY | G25: Residencial | H25: =I24+0.01 -> 41.01 | I25: 99999999999 | J25: 6.2762 | K25: 24.53 | L25: 46173 | M25: 0.09 | N25: =_xlfn.XLOOKUP(E25,ICMS!C:C,ICMS!D:D) -> 0.15 | O25: =1+O24 -> 24 | Q25: Não | R25: https://www.naturgy.com.br/atendimento/tarifas/tarifa_sao_paulo | S25: fevereiro, maio,agosto, novembro
A26: CONDOMINIOS | B26: SP (Naturgy) | C26: com pis/cofins e sem icms | D26: 1 | E26: SP | F26: NATURGY | G26: Residencial - Medição Coletiva | H26: 0 | I26: 100 | J26: 6.8116 | K26: 32.88 | L26: 46173 | M26: 0.09 | N26: =_xlfn.XLOOKUP(E26,ICMS!C:C,ICMS!D:D) -> 0.15 | O26: =1+O25 -> 25 | Q26: Não | R26: https://www.naturgy.com.br/atendimento/tarifas/tarifa_sao_paulo | S26: fevereiro, maio,agosto, novembro
A27: CONDOMINIOS | B27: SP (Naturgy) | C27: com pis/cofins e sem icms | D27: 2 | E27: SP | F27: NATURGY | G27: Residencial - Medição Coletiva | H27: =I26+0.01 -> 100.01 | I27: 300 | J27: 6.4161 | K27: 49.32 | L27: 46173 | M27: 0.09 | N27: =_xlfn.XLOOKUP(E27,ICMS!C:C,ICMS!D:D) -> 0.15 | O27: =1+O26 -> 26 | Q27: Não | R27: https://www.naturgy.com.br/atendimento/tarifas/tarifa_sao_paulo | S27: fevereiro, maio,agosto, novembro
A28: CONDOMINIOS | B28: SP (Naturgy) | C28: com pis/cofins e sem icms | D28: 3 | E28: SP | F28: NATURGY | G28: Residencial - Medição Coletiva | H28: =I27+0.01 -> 300.01 | I28: 99999999999 | J28: 6.2162 | K28: 98.64 | L28: 46173 | M28: 0.09 | N28: =_xlfn.XLOOKUP(E28,ICMS!C:C,ICMS!D:D) -> 0.15 | O28: =1+O27 -> 27 | Q28: Não | R28: https://www.naturgy.com.br/atendimento/tarifas/tarifa_sao_paulo | S28: fevereiro, maio,agosto, novembro
A29: COMERCIAL E SERVIÇOS | B29: SP (Naturgy) | C29: com pis/cofins e sem icms | D29: 1 | E29: SP | F29: NATURGY | G29: Comercial | H29: 0 | I29: 150 | J29: 7.0357 | K29: 67.23 | L29: 46173 | M29: 0.09 | N29: =_xlfn.XLOOKUP(E29,ICMS!C:C,ICMS!D:D) -> 0.15 | O29: =1+O28 -> 28 | Q29: Não | R29: https://www.naturgy.com.br/atendimento/tarifas/tarifa_sao_paulo | S29: fevereiro, maio,agosto, novembro
A30: COMERCIAL E SERVIÇOS | B30: SP (Naturgy) | C30: com pis/cofins e sem icms | D30: 2 | E30: SP | F30: NATURGY | G30: Comercial | H30: =I29+0.01 -> 150.01 | I30: 300 | J30: 6.3634 | K30: 105.06 | L30: 46173 | M30: 0.09 | N30: =_xlfn.XLOOKUP(E30,ICMS!C:C,ICMS!D:D) -> 0.15 | O30: =1+O29 -> 29 | Q30: Não | R30: https://www.naturgy.com.br/atendimento/tarifas/tarifa_sao_paulo | S30: fevereiro, maio,agosto, novembro
A31: COMERCIAL E SERVIÇOS | B31: SP (Naturgy) | C31: com pis/cofins e sem icms | D31: 3 | E31: SP | F31: NATURGY | G31: Comercial | H31: =I30+0.01 -> 300.01 | I31: 1000 | J31: 5.6249 | K31: 450.46 | L31: 46173 | M31: 0.09 | N31: =_xlfn.XLOOKUP(E31,ICMS!C:C,ICMS!D:D) -> 0.15 | O31: =1+O30 -> 30 | Q31: Não | R31: https://www.naturgy.com.br/atendimento/tarifas/tarifa_sao_paulo | S31: fevereiro, maio,agosto, novembro
A32: COMERCIAL E SERVIÇOS | B32: SP (Naturgy) | C32: com pis/cofins e sem icms | D32: 4 | E32: SP | F32: NATURGY | G32: Comercial | H32: =I31+0.01 -> 1000.01 | I32: 3000 | J32: 4.5146 | K32: 1801.81 | L32: 46173 | M32: 0.09 | N32: =_xlfn.XLOOKUP(E32,ICMS!C:C,ICMS!D:D) -> 0.15 | O32: =1+O31 -> 31 | Q32: Não | R32: https://www.naturgy.com.br/atendimento/tarifas/tarifa_sao_paulo | S32: fevereiro, maio,agosto, novembro
A33: COMERCIAL E SERVIÇOS | B33: SP (Naturgy) | C33: com pis/cofins e sem icms | D33: 5 | E33: SP | F33: NATURGY | G33: Comercial | H33: =I31+0.01 -> 1000.01 | I33: 99999999999 | J33: 4.2047 | K33: 4370.43 | L33: 46173 | M33: 0.09 | N33: =_xlfn.XLOOKUP(E33,ICMS!C:C,ICMS!D:D) -> 0.15 | O33: =1+O32 -> 32 | Q33: Não | R33: https://www.naturgy.com.br/atendimento/tarifas/tarifa_sao_paulo | S33: fevereiro, maio,agosto, novembro
A34: INDUSTRIAL | B34: SP (Naturgy) | C34: com pis/cofins e sem icms | D34: 1 | E34: SP | F34: NATURGY | G34: Industrial | H34: 0 | I34: 5000 | J34: 6.3259 | K34: 573.69 | L34: 46173 | M34: 0.09 | N34: =_xlfn.XLOOKUP(E34,ICMS!C:C,ICMS!D:D) -> 0.15 | O34: =1+O33 -> 33 | Q34: Não | R34: https://www.naturgy.com.br/atendimento/tarifas/tarifa_sao_paulo | S34: fevereiro, maio,agosto, novembro
A35: INDUSTRIAL | B35: SP (Naturgy) | C35: com pis/cofins e sem icms | D35: 2 | E35: SP | F35: NATURGY | G35: Industrial | H35: =I34+0.01 -> 5000.01 | I35: 50000 | J35: 4.2829 | K35: 11476.17 | L35: 46173 | M35: 0.09 | N35: =_xlfn.XLOOKUP(E35,ICMS!C:C,ICMS!D:D) -> 0.15 | O35: =1+O34 -> 34 | Q35: Não | R35: https://www.naturgy.com.br/atendimento/tarifas/tarifa_sao_paulo | S35: fevereiro, maio,agosto, novembro
A36: INDUSTRIAL | B36: SP (Naturgy) | C36: com pis/cofins e sem icms | D36: 3 | E36: SP | F36: NATURGY | G36: Industrial | H36: =I35+0.01 -> 50000.01 | I36: 300000 | J36: 3.3745 | K36: 53176.14 | L36: 46173 | M36: 0.09 | N36: =_xlfn.XLOOKUP(E36,ICMS!C:C,ICMS!D:D) -> 0.15 | O36: =1+O35 -> 35 | Q36: Não | R36: https://www.naturgy.com.br/atendimento/tarifas/tarifa_sao_paulo | S36: fevereiro, maio,agosto, novembro
A37: INDUSTRIAL | B37: SP (Naturgy) | C37: com pis/cofins e sem icms | D37: 4 | E37: SP | F37: NATURGY | G37: Industrial | H37: =I36+0.01 -> 300000.01 | I37: 500000 | J37: 3.1407 | K37: 138253.36 | L37: 46173 | M37: 0.09 | N37: =_xlfn.XLOOKUP(E37,ICMS!C:C,ICMS!D:D) -> 0.15 | O37: =1+O36 -> 36 | Q37: Não | R37: https://www.naturgy.com.br/atendimento/tarifas/tarifa_sao_paulo | S37: fevereiro, maio,agosto, novembro
A38: INDUSTRIAL | B38: SP (Naturgy) | C38: com pis/cofins e sem icms | D38: 5 | E38: SP | F38: NATURGY | G38: Industrial | H38: =I37+0.01 -> 500000.01 | I38: 2000000 | J38: 2.9094 | K38: 152827.11 | L38: 46173 | M38: 0.09 | N38: =_xlfn.XLOOKUP(E38,ICMS!C:C,ICMS!D:D) -> 0.15 | O38: =1+O37 -> 37 | Q38: Não | R38: https://www.naturgy.com.br/atendimento/tarifas/tarifa_sao_paulo | S38: fevereiro, maio,agosto, novembro
A39: INDUSTRIAL | B39: SP (Naturgy) | C39: com pis/cofins e sem icms | D39: 6 | E39: SP | F39: NATURGY | G39: Industrial | H39: =I38+0.01 -> 2000000 | I39: 5000000 | J39: 2.8248 | K39: 164528.82 | L39: 46173 | M39: 0.09 | N39: =_xlfn.XLOOKUP(E39,ICMS!C:C,ICMS!D:D) -> 0.15 | O39: =1+O38 -> 38 | Q39: Não | R39: https://www.naturgy.com.br/atendimento/tarifas/tarifa_sao_paulo | S39: fevereiro, maio,agosto, novembro
A40: INDUSTRIAL | B40: SP (Naturgy) | C40: com pis/cofins e sem icms | D40: 7 | E40: SP | F40: NATURGY | G40: Industrial | H40: =I39+0.01 -> 5000000 | I40: 10000000 | J40: 2.7653 | K40: 210708.77 | L40: 46173 | M40: 0.09 | N40: =_xlfn.XLOOKUP(E40,ICMS!C:C,ICMS!D:D) -> 0.15 | O40: =1+O39 -> 39 | Q40: Não | R40: https://www.naturgy.com.br/atendimento/tarifas/tarifa_sao_paulo | S40: fevereiro, maio,agosto, novembro
A41: INDUSTRIAL | B41: SP (Naturgy) | C41: com pis/cofins e sem icms | D41: 8 | E41: SP | F41: NATURGY | G41: Industrial | H41: =I40+0.01 -> 10000000 | I41: 99999999999 | J41: 2.6457 | K41: 235476.06 | L41: 46173 | M41: 0.09 | N41: =_xlfn.XLOOKUP(E41,ICMS!C:C,ICMS!D:D) -> 0.15 | O41: =1+O40 -> 40 | Q41: Não | R41: https://www.naturgy.com.br/atendimento/tarifas/tarifa_sao_paulo | S41: fevereiro, maio,agosto, novembro
A42: REVENDA | B42: SP (Necta) | C42: com pis/cofins e sem icms | D42: 1 | E42: SP | F42: NECTA | G42: Residencial | H42: 0 | I42: 6 | J42: 3.926 | K42: 31.03 | L42: 46183 | M42: 0.0924 | N42: =_xlfn.XLOOKUP(E42,ICMS!C:C,ICMS!D:D) -> 0.15 | O42: =1+O41 -> 41 | Q42: Não | R42: https://www.arsesp.sp.gov.br/Paginas/Tarifas.aspx#gascanalizado | S42: março, junho, setembro, dezembro
A43: REVENDA | B43: SP (Necta) | C43: com pis/cofins e sem icms | D43: 2 | E43: SP | F43: NECTA | G43: Residencial | H43: =I42+0.01 -> 6.01 | I43: 99999999999 | J43: 9.015 | K43: 0 | L43: 46183 | M43: 0.0924 | N43: =_xlfn.XLOOKUP(E43,ICMS!C:C,ICMS!D:D) -> 0.15 | O43: =1+O42 -> 42 | Q43: Não | R43: https://www.arsesp.sp.gov.br/Paginas/Tarifas.aspx#gascanalizado | S43: março, junho, setembro, dezembro
A44: CONDOMINIOS | B44: SP (Necta) | C44: com pis/cofins e sem icms | D44: 1 | E44: SP | F44: NECTA | G44: Residencial - Medição Coletiva | H44: 0 | I44: 100 | J44: 7.86 | K44: 150.73 | L44: 46183 | M44: 0.0924 | N44: =_xlfn.XLOOKUP(E44,ICMS!C:C,ICMS!D:D) -> 0.15 | O44: =1+O43 -> 43 | Q44: Não | R44: https://www.arsesp.sp.gov.br/Paginas/Tarifas.aspx#gascanalizado | S44: março, junho, setembro, dezembro
A45: CONDOMINIOS | B45: SP (Necta) | C45: com pis/cofins e sem icms | D45: 2 | E45: SP | F45: NECTA | G45: Residencial - Medição Coletiva | H45: =I44+0.01 -> 100.01 | I45: 300 | J45: 7.59 | K45: 177.65 | L45: 46183 | M45: 0.0924 | N45: =_xlfn.XLOOKUP(E45,ICMS!C:C,ICMS!D:D) -> 0.15 | O45: =1+O44 -> 44 | Q45: Não | R45: https://www.arsesp.sp.gov.br/Paginas/Tarifas.aspx#gascanalizado | S45: março, junho, setembro, dezembro
A46: CONDOMINIOS | B46: SP (Necta) | C46: com pis/cofins e sem icms | D46: 3 | E46: SP | F46: NECTA | G46: Residencial - Medição Coletiva | H46: =I45+0.01 -> 300.01 | I46: 99999999999 | J46: 7.33 | K46: 258.4 | L46: 46183 | M46: 0.0924 | N46: =_xlfn.XLOOKUP(E46,ICMS!C:C,ICMS!D:D) -> 0.15 | O46: =1+O45 -> 45 | Q46: Não | R46: https://www.arsesp.sp.gov.br/Paginas/Tarifas.aspx#gascanalizado | S46: março, junho, setembro, dezembro
A47: COMERCIAL E SERVIÇOS | B47: SP (Necta) | C47: com pis/cofins e sem icms | D47: 1 | E47: SP | F47: NECTA | G47: Comercial | H47: 0 | I47: 150 | J47: 5.94 | K47: 52.16 | L47: 46183 | M47: 0.0924 | N47: =_xlfn.XLOOKUP(E47,ICMS!C:C,ICMS!D:D) -> 0.15 | O47: =1+O46 -> 46 | Q47: Não | R47: https://www.arsesp.sp.gov.br/Paginas/Tarifas.aspx#gascanalizado | S47: março, junho, setembro, dezembro
A48: COMERCIAL E SERVIÇOS | B48: SP (Necta) | C48: com pis/cofins e sem icms | D48: 2 | E48: SP | F48: NECTA | G48: Comercial | H48: =I47+0.01 -> 150.01 | I48: 300 | J48: 5.85 | K48: 68.31 | L48: 46183 | M48: 0.0924 | N48: =_xlfn.XLOOKUP(E48,ICMS!C:C,ICMS!D:D) -> 0.15 | O48: =1+O47 -> 47 | Q48: Não | R48: https://www.arsesp.sp.gov.br/Paginas/Tarifas.aspx#gascanalizado | S48: março, junho, setembro, dezembro
A49: COMERCIAL E SERVIÇOS | B49: SP (Necta) | C49: com pis/cofins e sem icms | D49: 3 | E49: SP | F49: NECTA | G49: Comercial | H49: =I48+0.01 -> 300.01 | I49: 1000 | J49: 5.62 | K49: 132.91 | L49: 46183 | M49: 0.0924 | N49: =_xlfn.XLOOKUP(E49,ICMS!C:C,ICMS!D:D) -> 0.15 | O49: =1+O48 -> 48 | Q49: Não | R49: https://www.arsesp.sp.gov.br/Paginas/Tarifas.aspx#gascanalizado | S49: março, junho, setembro, dezembro
A50: COMERCIAL E SERVIÇOS | B50: SP (Necta) | C50: com pis/cofins e sem icms | D50: 4 | E50: SP | F50: NECTA | G50: Comercial | H50: =I49+0.01 -> 1000.01 | I50: 3000 | J50: 5.15 | K50: 488.21 | L50: 46183 | M50: 0.0924 | N50: =_xlfn.XLOOKUP(E50,ICMS!C:C,ICMS!D:D) -> 0.15 | O50: =1+O49 -> 49 | Q50: Não | R50: https://www.arsesp.sp.gov.br/Paginas/Tarifas.aspx#gascanalizado | S50: março, junho, setembro, dezembro
A51: COMERCIAL E SERVIÇOS | B51: SP (Necta) | C51: com pis/cofins e sem icms | D51: 5 | E51: SP | F51: NECTA | G51: Comercial | H51: =I50+0.01 -> 3000.01 | I51: 99999999999 | J51: 3.98 | K51: 4041.2 | L51: 46183 | M51: 0.0924 | N51: =_xlfn.XLOOKUP(E51,ICMS!C:C,ICMS!D:D) -> 0.15 | O51: =1+O50 -> 50 | Q51: Não | R51: https://www.arsesp.sp.gov.br/Paginas/Tarifas.aspx#gascanalizado | S51: março, junho, setembro, dezembro
A52: INDUSTRIAL | B52: SP (Necta) | C52: com pis/cofins e sem icms | D52: 1 | E52: SP | F52: NECTA | G52: Industrial e Interruptível | H52: 0 | I52: 5000 | J52: 3.78 | K52: 499.31 | L52: 46183 | M52: 0.0924 | N52: =_xlfn.XLOOKUP(E52,ICMS!C:C,ICMS!D:D) -> 0.15 | O52: =1+O51 -> 51 | Q52: Não | R52: https://www.arsesp.sp.gov.br/Paginas/Tarifas.aspx#gascanalizado | S52: março, junho, setembro, dezembro
A53: INDUSTRIAL | B53: SP (Necta) | C53: com pis/cofins e sem icms | D53: 2 | E53: SP | F53: NECTA | G53: Industrial e Interruptível | H53: =I52+0.01 -> 5000.01 | I53: 50000 | J53: 3.62 | K53: 1306.8 | L53: 46183 | M53: 0.0924 | N53: =_xlfn.XLOOKUP(E53,ICMS!C:C,ICMS!D:D) -> 0.15 | O53: =1+O52 -> 52 | Q53: Não | R53: https://www.arsesp.sp.gov.br/Paginas/Tarifas.aspx#gascanalizado | S53: março, junho, setembro, dezembro
A54: INDUSTRIAL | B54: SP (Necta) | C54: com pis/cofins e sem icms | D54: 3 | E54: SP | F54: NECTA | G54: Industrial e Interruptível | H54: =I53+0.01 -> 50000.01 | I54: 100000 | J54: 3.56 | K54: 4536.79 | L54: 46183 | M54: 0.0924 | N54: =_xlfn.XLOOKUP(E54,ICMS!C:C,ICMS!D:D) -> 0.15 | O54: =1+O53 -> 53 | Q54: Não | R54: https://www.arsesp.sp.gov.br/Paginas/Tarifas.aspx#gascanalizado | S54: março, junho, setembro, dezembro
A55: INDUSTRIAL | B55: SP (Necta) | C55: com pis/cofins e sem icms | D55: 4 | E55: SP | F55: NECTA | G55: Industrial e Interruptível | H55: =I54+0.01 -> 100000.01 | I55: 300000 | J55: 3.41 | K55: 19610.08 | L55: 46183 | M55: 0.0924 | N55: =_xlfn.XLOOKUP(E55,ICMS!C:C,ICMS!D:D) -> 0.15 | O55: =1+O54 -> 54 | Q55: Não | R55: https://www.arsesp.sp.gov.br/Paginas/Tarifas.aspx#gascanalizado | S55: março, junho, setembro, dezembro
A56: INDUSTRIAL | B56: SP (Necta) | C56: com pis/cofins e sem icms | D56: 5 | E56: SP | F56: NECTA | G56: Industrial e Interruptível | H56: =I55+0.01 -> 300000.01 | I56: 650000 | J56: 3.24 | K56: 68059.94 | L56: 46183 | M56: 0.0924 | N56: =_xlfn.XLOOKUP(E56,ICMS!C:C,ICMS!D:D) -> 0.15 | O56: =1+O55 -> 55 | Q56: Não | R56: https://www.arsesp.sp.gov.br/Paginas/Tarifas.aspx#gascanalizado | S56: março, junho, setembro, dezembro
A57: INDUSTRIAL | B57: SP (Necta) | C57: com pis/cofins e sem icms | D57: 6 | E57: SP | F57: NECTA | G57: Industrial e Interruptível | H57: =I56+0.01 -> 650000.01 | I57: 99999999999 | J57: 3.08 | K57: 173034.63 | L57: 46183 | M57: 0.0924 | N57: =_xlfn.XLOOKUP(E57,ICMS!C:C,ICMS!D:D) -> 0.15 | O57: =1+O56 -> 56 | Q57: Não | R57: https://www.arsesp.sp.gov.br/Paginas/Tarifas.aspx#gascanalizado | S57: março, junho, setembro, dezembro
A58: CONDOMINIOS | B58: RJ (Capital + Reg. Metrop.) | C58: com pis/cofins/icms | D58: 1 | E58: RJ | F58: NATURGY (CEG) | G58: Residencial | H58: 0 | I58: 7 | J58: 9.5319 | K58: 0 | L58: 46174 | M58: 0.0925 | N58: =_xlfn.XLOOKUP(E58,ICMS!C:C,ICMS!D:D) -> 0.12 | O58: =1+O57 -> 57 | Q58: Sim | R58: https://www.naturgy.com.br/atendimento/tarifas/tarifa_rio_de_janeiro/ | S58: janeiro, fevereiro, maio, agosto, novembro.
A59: CONDOMINIOS | B59: RJ (Capital + Reg. Metrop.) | C59: com pis/cofins/icms | D59: 2 | E59: RJ | F59: NATURGY (CEG) | G59: Residencial | H59: =I58+0.01 -> 7.01 | I59: 23 | J59: 12.484 | K59: 0 | L59: 46174 | M59: 0.0925 | N59: =_xlfn.XLOOKUP(E59,ICMS!C:C,ICMS!D:D) -> 0.12 | O59: =1+O58 -> 58 | Q59: Sim | R59: https://www.naturgy.com.br/atendimento/tarifas/tarifa_rio_de_janeiro/ | S59: janeiro, fevereiro, maio, agosto, novembro.
A60: CONDOMINIOS | B60: RJ (Capital + Reg. Metrop.) | C60: com pis/cofins/icms | D60: 3 | E60: RJ | F60: NATURGY (CEG) | G60: Residencial | H60: =I59+0.01 -> 23.01 | I60: 83 | J60: 15.1543 | K60: 0 | L60: 46174 | M60: 0.0925 | N60: =_xlfn.XLOOKUP(E60,ICMS!C:C,ICMS!D:D) -> 0.12 | O60: =1+O59 -> 59 | Q60: Sim | R60: https://www.naturgy.com.br/atendimento/tarifas/tarifa_rio_de_janeiro/ | S60: janeiro, fevereiro, maio, agosto, novembro.
A61: CONDOMINIOS | B61: RJ (Capital + Reg. Metrop.) | C61: com pis/cofins/icms | D61: 4 | E61: RJ | F61: NATURGY (CEG) | G61: Residencial | H61: =I60+0.01 -> 83.01 | I61: 99999999999 | J61: 16.0012 | K61: 0 | L61: 46174 | M61: 0.0925 | N61: =_xlfn.XLOOKUP(E61,ICMS!C:C,ICMS!D:D) -> 0.12 | O61: =1+O60 -> 60 | Q61: Sim | R61: https://www.naturgy.com.br/atendimento/tarifas/tarifa_rio_de_janeiro/ | S61: janeiro, fevereiro, maio, agosto, novembro.
A62: REVENDA | B62: RJ (Capital + Reg. Metrop.) | C62: com pis/cofins/icms | D62: 1 | E62: RJ | F62: NATURGY (CEG) | G62: Residencial | H62: 0 | I62: 7 | J62: 9.5319 | K62: 0 | L62: 46174 | M62: 0.0925 | N62: =_xlfn.XLOOKUP(E62,ICMS!C:C,ICMS!D:D) -> 0.12 | O62: =1+O61 -> 61 | Q62: Sim | R62: https://www.naturgy.com.br/atendimento/tarifas/tarifa_rio_de_janeiro/ | S62: janeiro, fevereiro, maio, agosto, novembro.
A63: REVENDA | B63: RJ (Capital + Reg. Metrop.) | C63: com pis/cofins/icms | D63: 2 | E63: RJ | F63: NATURGY (CEG) | G63: Residencial | H63: =I62+0.01 -> 7.01 | I63: 23 | J63: 12.484 | K63: 0 | L63: 46174 | M63: 0.0925 | N63: =_xlfn.XLOOKUP(E63,ICMS!C:C,ICMS!D:D) -> 0.12 | O63: =1+O62 -> 62 | Q63: Sim | R63: https://www.naturgy.com.br/atendimento/tarifas/tarifa_rio_de_janeiro/ | S63: janeiro, fevereiro, maio, agosto, novembro.
A64: REVENDA | B64: RJ (Capital + Reg. Metrop.) | C64: com pis/cofins/icms | D64: 3 | E64: RJ | F64: NATURGY (CEG) | G64: Residencial | H64: =I63+0.01 -> 23.01 | I64: 83 | J64: 15.1543 | K64: 0 | L64: 46174 | M64: 0.0925 | N64: =_xlfn.XLOOKUP(E64,ICMS!C:C,ICMS!D:D) -> 0.12 | O64: =1+O63 -> 63 | Q64: Sim | R64: https://www.naturgy.com.br/atendimento/tarifas/tarifa_rio_de_janeiro/ | S64: janeiro, fevereiro, maio, agosto, novembro.
A65: REVENDA | B65: RJ (Capital + Reg. Metrop.) | C65: com pis/cofins/icms | D65: 4 | E65: RJ | F65: NATURGY (CEG) | G65: Residencial | H65: =I64+0.01 -> 83.01 | I65: 99999999999 | J65: 16.0012 | K65: 0 | L65: 46174 | M65: 0.0925 | N65: =_xlfn.XLOOKUP(E65,ICMS!C:C,ICMS!D:D) -> 0.12 | O65: =1+O64 -> 64 | Q65: Sim | R65: https://www.naturgy.com.br/atendimento/tarifas/tarifa_rio_de_janeiro/ | S65: janeiro, fevereiro, maio, agosto, novembro.
A66: COMERCIAL E SERVIÇOS | B66: RJ (Capital + Reg. Metrop.) | C66: com pis/cofins/icms | D66: 1 | E66: RJ | F66: NATURGY (CEG) | G66: Comercial e Outros | H66: 0 | I66: 200 | J66: 9.3028 | K66: 0 | L66: 46174 | M66: 0.0925 | N66: =_xlfn.XLOOKUP(E66,ICMS!C:C,ICMS!D:D) -> 0.12 | O66: =1+O65 -> 65 | Q66: Sim | R66: https://www.naturgy.com.br/atendimento/tarifas/tarifa_rio_de_janeiro/ | S66: janeiro, fevereiro, maio, agosto, novembro.
A67: COMERCIAL E SERVIÇOS | B67: RJ (Capital + Reg. Metrop.) | C67: com pis/cofins/icms | D67: 2 | E67: RJ | F67: NATURGY (CEG) | G67: Comercial e Outros | H67: =I66+0.01 -> 200.01 | I67: 500 | J67: 9.0294 | K67: 0 | L67: 46174 | M67: 0.0925 | N67: =_xlfn.XLOOKUP(E67,ICMS!C:C,ICMS!D:D) -> 0.12 | O67: =1+O66 -> 66 | Q67: Sim | R67: https://www.naturgy.com.br/atendimento/tarifas/tarifa_rio_de_janeiro/ | S67: janeiro, fevereiro, maio, agosto, novembro.
A68: COMERCIAL E SERVIÇOS | B68: RJ (Capital + Reg. Metrop.) | C68: com pis/cofins/icms | D68: 3 | E68: RJ | F68: NATURGY (CEG) | G68: Comercial e Outros | H68: =I67+0.01 -> 500.01 | I68: 2000 | J68: 8.7566 | K68: 0 | L68: 46174 | M68: 0.0925 | N68: =_xlfn.XLOOKUP(E68,ICMS!C:C,ICMS!D:D) -> 0.12 | O68: =1+O67 -> 67 | Q68: Sim | R68: https://www.naturgy.com.br/atendimento/tarifas/tarifa_rio_de_janeiro/ | S68: janeiro, fevereiro, maio, agosto, novembro.
A69: COMERCIAL E SERVIÇOS | B69: RJ (Capital + Reg. Metrop.) | C69: com pis/cofins/icms | D69: 4 | E69: RJ | F69: NATURGY (CEG) | G69: Comercial e Outros | H69: =I68+0.01 -> 2000.01 | I69: 20000 | J69: 8.4841 | K69: 0 | L69: 46174 | M69: 0.0925 | N69: =_xlfn.XLOOKUP(E69,ICMS!C:C,ICMS!D:D) -> 0.12 | O69: =1+O68 -> 68 | Q69: Sim | R69: https://www.naturgy.com.br/atendimento/tarifas/tarifa_rio_de_janeiro/ | S69: janeiro, fevereiro, maio, agosto, novembro.
A70: COMERCIAL E SERVIÇOS | B70: RJ (Capital + Reg. Metrop.) | C70: com pis/cofins/icms | D70: 5 | E70: RJ | F70: NATURGY (CEG) | G70: Comercial e Outros | H70: =I69+0.01 -> 20000.01 | I70: 50000 | J70: 8.211 | K70: 0 | L70: 46174 | M70: 0.0925 | N70: =_xlfn.XLOOKUP(E70,ICMS!C:C,ICMS!D:D) -> 0.12 | O70: =1+O69 -> 69 | Q70: Sim | R70: https://www.naturgy.com.br/atendimento/tarifas/tarifa_rio_de_janeiro/ | S70: janeiro, fevereiro, maio, agosto, novembro.
A71: COMERCIAL E SERVIÇOS | B71: RJ (Capital + Reg. Metrop.) | C71: com pis/cofins/icms | D71: 6 | E71: RJ | F71: NATURGY (CEG) | G71: Comercial e Outros | H71: =I70+0.01 -> 50000.01 | I71: 99999999999 | J71: 7.938 | K71: 0 | L71: 46174 | M71: 0.0925 | N71: =_xlfn.XLOOKUP(E71,ICMS!C:C,ICMS!D:D) -> 0.12 | O71: =1+O70 -> 70 | Q71: Sim | R71: https://www.naturgy.com.br/atendimento/tarifas/tarifa_rio_de_janeiro/ | S71: janeiro, fevereiro, maio, agosto, novembro.
A72: INDUSTRIAL | B72: RJ (Capital + Reg. Metrop.) | C72: com pis/cofins/icms | D72: 1 | E72: RJ | F72: NATURGY (CEG) | G72: Industrial | H72: 0 | I72: 200 | J72: 5.4475 | K72: 0 | L72: 46174 | M72: 0.0925 | N72: =_xlfn.XLOOKUP(E72,ICMS!C:C,ICMS!D:D) -> 0.12 | O72: =1+O71 -> 71 | Q72: Sim | R72: https://www.naturgy.com.br/atendimento/tarifas/tarifa_rio_de_janeiro/ | S72: janeiro, fevereiro, maio, agosto, novembro.
A73: INDUSTRIAL | B73: RJ (Capital + Reg. Metrop.) | C73: com pis/cofins/icms | D73: 2 | E73: RJ | F73: NATURGY (CEG) | G73: Industrial | H73: =I72+0.01 -> 200.01 | I73: 2000 | J73: 5.2863 | K73: 0 | L73: 46174 | M73: 0.0925 | N73: =_xlfn.XLOOKUP(E73,ICMS!C:C,ICMS!D:D) -> 0.12 | O73: =1+O72 -> 72 | Q73: Sim | R73: https://www.naturgy.com.br/atendimento/tarifas/tarifa_rio_de_janeiro/ | S73: janeiro, fevereiro, maio, agosto, novembro.
A74: INDUSTRIAL | B74: RJ (Capital + Reg. Metrop.) | C74: com pis/cofins/icms | D74: 3 | E74: RJ | F74: NATURGY (CEG) | G74: Industrial | H74: =I73+0.01 -> 2000.01 | I74: 10000 | J74: 5.1895 | K74: 0 | L74: 46174 | M74: 0.0925 | N74: =_xlfn.XLOOKUP(E74,ICMS!C:C,ICMS!D:D) -> 0.12 | O74: =1+O73 -> 73 | Q74: Sim | R74: https://www.naturgy.com.br/atendimento/tarifas/tarifa_rio_de_janeiro/ | S74: janeiro, fevereiro, maio, agosto, novembro.
A75: INDUSTRIAL | B75: RJ (Capital + Reg. Metrop.) | C75: com pis/cofins/icms | D75: 4 | E75: RJ | F75: NATURGY (CEG) | G75: Industrial | H75: =I74+0.01 -> 10000.01 | I75: 50000 | J75: 4.662 | K75: 0 | L75: 46174 | M75: 0.0925 | N75: =_xlfn.XLOOKUP(E75,ICMS!C:C,ICMS!D:D) -> 0.12 | O75: =1+O74 -> 74 | Q75: Sim | R75: https://www.naturgy.com.br/atendimento/tarifas/tarifa_rio_de_janeiro/ | S75: janeiro, fevereiro, maio, agosto, novembro.
A76: INDUSTRIAL | B76: RJ (Capital + Reg. Metrop.) | C76: com pis/cofins/icms | D76: 5 | E76: RJ | F76: NATURGY (CEG) | G76: Industrial | H76: =I75+0.01 -> 50000.01 | I76: 100000 | J76: 4.3455 | K76: 0 | L76: 46174 | M76: 0.0925 | N76: =_xlfn.XLOOKUP(E76,ICMS!C:C,ICMS!D:D) -> 0.12 | O76: =1+O75 -> 75 | Q76: Sim | R76: https://www.naturgy.com.br/atendimento/tarifas/tarifa_rio_de_janeiro/ | S76: janeiro, fevereiro, maio, agosto, novembro.
A77: INDUSTRIAL | B77: RJ (Capital + Reg. Metrop.) | C77: com pis/cofins/icms | D77: 6 | E77: RJ | F77: NATURGY (CEG) | G77: Industrial | H77: =I76+0.01 -> 100000.01 | I77: 300000 | J77: 4.0081 | K77: 0 | L77: 46174 | M77: 0.0925 | N77: =_xlfn.XLOOKUP(E77,ICMS!C:C,ICMS!D:D) -> 0.12 | O77: =1+O76 -> 76 | Q77: Sim | R77: https://www.naturgy.com.br/atendimento/tarifas/tarifa_rio_de_janeiro/ | S77: janeiro, fevereiro, maio, agosto, novembro.
A78: INDUSTRIAL | B78: RJ (Capital + Reg. Metrop.) | C78: com pis/cofins/icms | D78: 7 | E78: RJ | F78: NATURGY (CEG) | G78: Industrial | H78: =I77+0.01 -> 300000.01 | I78: 600000 | J78: 3.6085 | K78: 0 | L78: 46174 | M78: 0.0925 | N78: =_xlfn.XLOOKUP(E78,ICMS!C:C,ICMS!D:D) -> 0.12 | O78: =1+O77 -> 77 | Q78: Sim | R78: https://www.naturgy.com.br/atendimento/tarifas/tarifa_rio_de_janeiro/ | S78: janeiro, fevereiro, maio, agosto, novembro.
A79: INDUSTRIAL | B79: RJ (Capital + Reg. Metrop.) | C79: com pis/cofins/icms | D79: 8 | E79: RJ | F79: NATURGY (CEG) | G79: Industrial | H79: =I78+0.01 -> 600000.01 | I79: 1500000 | J79: 3.5981 | K79: 0 | L79: 46174 | M79: 0.0925 | N79: =_xlfn.XLOOKUP(E79,ICMS!C:C,ICMS!D:D) -> 0.12 | O79: =1+O78 -> 78 | Q79: Sim | R79: https://www.naturgy.com.br/atendimento/tarifas/tarifa_rio_de_janeiro/ | S79: janeiro, fevereiro, maio, agosto, novembro.
A80: INDUSTRIAL | B80: RJ (Capital + Reg. Metrop.) | C80: com pis/cofins/icms | D80: 9 | E80: RJ | F80: NATURGY (CEG) | G80: Industrial | H80: =I79+0.01 -> 1500000 | I80: 3000000 | J80: 3.5688 | K80: 0 | L80: 46174 | M80: 0.0925 | N80: =_xlfn.XLOOKUP(E80,ICMS!C:C,ICMS!D:D) -> 0.12 | O80: =1+O79 -> 79 | Q80: Sim | R80: https://www.naturgy.com.br/atendimento/tarifas/tarifa_rio_de_janeiro/ | S80: janeiro, fevereiro, maio, agosto, novembro.
A81: INDUSTRIAL | B81: RJ (Capital + Reg. Metrop.) | C81: com pis/cofins/icms | D81: 10 | E81: RJ | F81: NATURGY (CEG) | G81: Industrial | H81: =I80+0.01 -> 3000000 | I81: 99999999999 | J81: 3.4698 | K81: 0 | L81: 46174 | M81: 0.0925 | N81: =_xlfn.XLOOKUP(E81,ICMS!C:C,ICMS!D:D) -> 0.12 | O81: =1+O80 -> 80 | Q81: Sim | R81: https://www.naturgy.com.br/atendimento/tarifas/tarifa_rio_de_janeiro/ | S81: janeiro, fevereiro, maio, agosto, novembro.
A82: CONDOMINIOS | B82: RJ (Interior) | C82: com pis/cofins/icms | D82: 1 | E82: RJ | F82: NATURGY (CEG-RIO) | G82: Residencial | H82: 0 | I82: 7 | J82: 7.2958 | K82: 0 | L82: 46174 | M82: 0.0925 | N82: =_xlfn.XLOOKUP(E82,ICMS!C:C,ICMS!D:D) -> 0.12 | O82: =1+O81 -> 81 | Q82: Sim | R82: https://www.naturgy.com.br/atendimento/tarifas/tarifa_rio_de_janeiro/ | S82: janeiro, fevereiro, maio, agosto, novembro.
A83: CONDOMINIOS | B83: RJ (Interior) | C83: com pis/cofins/icms | D83: 2 | E83: RJ | F83: NATURGY (CEG-RIO) | G83: Residencial | H83: =I82+0.01 -> 7.01 | I83: 23 | J83: 9.2704 | K83: 0 | L83: 46174 | M83: 0.0925 | N83: =_xlfn.XLOOKUP(E83,ICMS!C:C,ICMS!D:D) -> 0.12 | O83: =1+O82 -> 82 | Q83: Sim | R83: https://www.naturgy.com.br/atendimento/tarifas/tarifa_rio_de_janeiro/ | S83: janeiro, fevereiro, maio, agosto, novembro.
A84: CONDOMINIOS | B84: RJ (Interior) | C84: com pis/cofins/icms | D84: 3 | E84: RJ | F84: NATURGY (CEG-RIO) | G84: Residencial | H84: =I83+0.01 -> 23.01 | I84: 83 | J84: 11.0781 | K84: 0 | L84: 46174 | M84: 0.0925 | N84: =_xlfn.XLOOKUP(E84,ICMS!C:C,ICMS!D:D) -> 0.12 | O84: =1+O83 -> 83 | Q84: Sim | R84: https://www.naturgy.com.br/atendimento/tarifas/tarifa_rio_de_janeiro/ | S84: janeiro, fevereiro, maio, agosto, novembro.
A85: CONDOMINIOS | B85: RJ (Interior) | C85: com pis/cofins/icms | D85: 4 | E85: RJ | F85: NATURGY (CEG-RIO) | G85: Residencial | H85: =I84+0.01 -> 83.01 | I85: 99999999999 | J85: 12.3523 | K85: 0 | L85: 46174 | M85: 0.0925 | N85: =_xlfn.XLOOKUP(E85,ICMS!C:C,ICMS!D:D) -> 0.12 | O85: =1+O84 -> 84 | Q85: Sim | R85: https://www.naturgy.com.br/atendimento/tarifas/tarifa_rio_de_janeiro/ | S85: janeiro, fevereiro, maio, agosto, novembro.
A86: REVENDA | B86: RJ (Interior) | C86: com pis/cofins/icms | D86: 1 | E86: RJ | F86: NATURGY (CEG-RIO) | G86: Residencial | H86: 0 | I86: 7 | J86: 7.2958 | K86: 0 | L86: 46174 | M86: 0.0925 | N86: =_xlfn.XLOOKUP(E86,ICMS!C:C,ICMS!D:D) -> 0.12 | O86: =1+O85 -> 85 | Q86: Sim | R86: https://www.naturgy.com.br/atendimento/tarifas/tarifa_rio_de_janeiro/ | S86: janeiro, fevereiro, maio, agosto, novembro.
A87: REVENDA | B87: RJ (Interior) | C87: com pis/cofins/icms | D87: 2 | E87: RJ | F87: NATURGY (CEG-RIO) | G87: Residencial | H87: =I86+0.01 -> 7.01 | I87: 23 | J87: 9.2704 | K87: 0 | L87: 46174 | M87: 0.0925 | N87: =_xlfn.XLOOKUP(E87,ICMS!C:C,ICMS!D:D) -> 0.12 | O87: =1+O86 -> 86 | Q87: Sim | R87: https://www.naturgy.com.br/atendimento/tarifas/tarifa_rio_de_janeiro/ | S87: janeiro, fevereiro, maio, agosto, novembro.
A88: REVENDA | B88: RJ (Interior) | C88: com pis/cofins/icms | D88: 3 | E88: RJ | F88: NATURGY (CEG-RIO) | G88: Residencial | H88: =I87+0.01 -> 23.01 | I88: 83 | J88: 11.0781 | K88: 0 | L88: 46174 | M88: 0.0925 | N88: =_xlfn.XLOOKUP(E88,ICMS!C:C,ICMS!D:D) -> 0.12 | O88: =1+O87 -> 87 | Q88: Sim | R88: https://www.naturgy.com.br/atendimento/tarifas/tarifa_rio_de_janeiro/ | S88: janeiro, fevereiro, maio, agosto, novembro.
A89: REVENDA | B89: RJ (Interior) | C89: com pis/cofins/icms | D89: 4 | E89: RJ | F89: NATURGY (CEG-RIO) | G89: Residencial | H89: =I88+0.01 -> 83.01 | I89: 99999999999 | J89: 12.3523 | K89: 0 | L89: 46174 | M89: 0.0925 | N89: =_xlfn.XLOOKUP(E89,ICMS!C:C,ICMS!D:D) -> 0.12 | O89: =1+O88 -> 88 | Q89: Sim | R89: https://www.naturgy.com.br/atendimento/tarifas/tarifa_rio_de_janeiro/ | S89: janeiro, fevereiro, maio, agosto, novembro.
A90: COMERCIAL E SERVIÇOS | B90: RJ (Interior) | C90: com pis/cofins/icms | D90: 1 | E90: RJ | F90: NATURGY (CEG-RIO) | G90: Comercial e Outros | H90: 0 | I90: 200 | J90: 6.239 | K90: 0 | L90: 46174 | M90: 0.0925 | N90: =_xlfn.XLOOKUP(E90,ICMS!C:C,ICMS!D:D) -> 0.12 | O90: =1+O89 -> 89 | Q90: Sim | R90: https://www.naturgy.com.br/atendimento/tarifas/tarifa_rio_de_janeiro/ | S90: janeiro, fevereiro, maio, agosto, novembro.
A91: COMERCIAL E SERVIÇOS | B91: RJ (Interior) | C91: com pis/cofins/icms | D91: 2 | E91: RJ | F91: NATURGY (CEG-RIO) | G91: Comercial e Outros | H91: =I90+0.01 -> 200.01 | I91: 500 | J91: 6.1659 | K91: 0 | L91: 46174 | M91: 0.0925 | N91: =_xlfn.XLOOKUP(E91,ICMS!C:C,ICMS!D:D) -> 0.12 | O91: =1+O90 -> 90 | Q91: Sim | R91: https://www.naturgy.com.br/atendimento/tarifas/tarifa_rio_de_janeiro/ | S91: janeiro, fevereiro, maio, agosto, novembro.
A92: COMERCIAL E SERVIÇOS | B92: RJ (Interior) | C92: com pis/cofins/icms | D92: 3 | E92: RJ | F92: NATURGY (CEG-RIO) | G92: Comercial e Outros | H92: =I91+0.01 -> 500.01 | I92: 2000 | J92: 5.039 | K92: 0 | L92: 46174 | M92: 0.0925 | N92: =_xlfn.XLOOKUP(E92,ICMS!C:C,ICMS!D:D) -> 0.12 | O92: =1+O91 -> 91 | Q92: Sim | R92: https://www.naturgy.com.br/atendimento/tarifas/tarifa_rio_de_janeiro/ | S92: janeiro, fevereiro, maio, agosto, novembro.
A93: COMERCIAL E SERVIÇOS | B93: RJ (Interior) | C93: com pis/cofins/icms | D93: 4 | E93: RJ | F93: NATURGY (CEG-RIO) | G93: Comercial e Outros | H93: =I92+0.01 -> 2000.01 | I93: 20000 | J93: 4.9187 | K93: 0 | L93: 46174 | M93: 0.0925 | N93: =_xlfn.XLOOKUP(E93,ICMS!C:C,ICMS!D:D) -> 0.12 | O93: =1+O92 -> 92 | Q93: Sim | R93: https://www.naturgy.com.br/atendimento/tarifas/tarifa_rio_de_janeiro/ | S93: janeiro, fevereiro, maio, agosto, novembro.
A94: COMERCIAL E SERVIÇOS | B94: RJ (Interior) | C94: com pis/cofins/icms | D94: 5 | E94: RJ | F94: NATURGY (CEG-RIO) | G94: Comercial e Outros | H94: =I93+0.01 -> 20000.01 | I94: 50000 | J94: 4.8141 | K94: 0 | L94: 46174 | M94: 0.0925 | N94: =_xlfn.XLOOKUP(E94,ICMS!C:C,ICMS!D:D) -> 0.12 | O94: =1+O93 -> 93 | Q94: Sim | R94: https://www.naturgy.com.br/atendimento/tarifas/tarifa_rio_de_janeiro/ | S94: janeiro, fevereiro, maio, agosto, novembro.
A95: COMERCIAL E SERVIÇOS | B95: RJ (Interior) | C95: com pis/cofins/icms | D95: 6 | E95: RJ | F95: NATURGY (CEG-RIO) | G95: Comercial e Outros | H95: =I94+0.01 -> 50000.01 | I95: 99999999999 | J95: 4.7095 | K95: 0 | L95: 46174 | M95: 0.0925 | N95: =_xlfn.XLOOKUP(E95,ICMS!C:C,ICMS!D:D) -> 0.12 | O95: =1+O94 -> 94 | Q95: Sim | R95: https://www.naturgy.com.br/atendimento/tarifas/tarifa_rio_de_janeiro/ | S95: janeiro, fevereiro, maio, agosto, novembro.
A96: INDUSTRIAL | B96: RJ (Interior) | C96: com pis/cofins/icms | D96: 1 | E96: RJ | F96: NATURGY (CEG-RIO) | G96: Industrial | H96: 0 | I96: 200 | J96: 5.1584 | K96: 0 | L96: 46174 | M96: 0.0925 | N96: =_xlfn.XLOOKUP(E96,ICMS!C:C,ICMS!D:D) -> 0.12 | O96: =1+O95 -> 95 | Q96: Sim | R96: https://www.naturgy.com.br/atendimento/tarifas/tarifa_rio_de_janeiro/ | S96: janeiro, fevereiro, maio, agosto, novembro.
A97: INDUSTRIAL | B97: RJ (Interior) | C97: com pis/cofins/icms | D97: 2 | E97: RJ | F97: NATURGY (CEG-RIO) | G97: Industrial | H97: =I96+0.01 -> 200.01 | I97: 2000 | J97: 5.0139 | K97: 0 | L97: 46174 | M97: 0.0925 | N97: =_xlfn.XLOOKUP(E97,ICMS!C:C,ICMS!D:D) -> 0.12 | O97: =1+O96 -> 96 | Q97: Sim | R97: https://www.naturgy.com.br/atendimento/tarifas/tarifa_rio_de_janeiro/ | S97: janeiro, fevereiro, maio, agosto, novembro.
A98: INDUSTRIAL | B98: RJ (Interior) | C98: com pis/cofins/icms | D98: 3 | E98: RJ | F98: NATURGY (CEG-RIO) | G98: Industrial | H98: =I97+0.01 -> 2000.01 | I98: 10000 | J98: 4.9272 | K98: 0 | L98: 46174 | M98: 0.0925 | N98: =_xlfn.XLOOKUP(E98,ICMS!C:C,ICMS!D:D) -> 0.12 | O98: =1+O97 -> 97 | Q98: Sim | R98: https://www.naturgy.com.br/atendimento/tarifas/tarifa_rio_de_janeiro/ | S98: janeiro, fevereiro, maio, agosto, novembro.
A99: INDUSTRIAL | B99: RJ (Interior) | C99: com pis/cofins/icms | D99: 4 | E99: RJ | F99: NATURGY (CEG-RIO) | G99: Industrial | H99: =I98+0.01 -> 10000.01 | I99: 50000 | J99: 4.3289 | K99: 0 | L99: 46174 | M99: 0.0925 | N99: =_xlfn.XLOOKUP(E99,ICMS!C:C,ICMS!D:D) -> 0.12 | O99: =1+O98 -> 98 | Q99: Sim | R99: https://www.naturgy.com.br/atendimento/tarifas/tarifa_rio_de_janeiro/ | S99: janeiro, fevereiro, maio, agosto, novembro.
A100: INDUSTRIAL | B100: RJ (Interior) | C100: com pis/cofins/icms | D100: 5 | E100: RJ | F100: NATURGY (CEG-RIO) | G100: Industrial | H100: =I99+0.01 -> 50000.01 | I100: 100000 | J100: 4.0705 | K100: 0 | L100: 46174 | M100: 0.0925 | N100: =_xlfn.XLOOKUP(E100,ICMS!C:C,ICMS!D:D) -> 0.12 | O100: =1+O99 -> 99 | Q100: Sim | R100: https://www.naturgy.com.br/atendimento/tarifas/tarifa_rio_de_janeiro/ | S100: janeiro, fevereiro, maio, agosto, novembro.
...

Sheet Calculo impostos
B2: com pis/cofins de 9% | C2: 2.8763
B3: sem pis/cofins de 9% | C3: =C2*(1-9/100) -> 2.617433 | D3: =Tarifario!#REF!*(1-8.9/100) -> #REF!
B4: com pis/cofins de 9% e icms de 15% | C4: =C3/(1-9/100)/(1-15/100) -> 3.3838824 | D4: =Tarifario!#REF!/(1-8.9/100)/(1-15/100) -> #REF!
B5: sem pis/cofins de 9% e icms de 15% | C5: =C4*(1-9/100)*(1-15/100) -> 2.617433

Sheet uf sem GN
A1: UF | B1: Tem GN?
A2: AC | B2: Nao
A3: AP | B3: Nao
A4: DF | B4: Nao
A5: GO | B5: Nao
A6: MA | B6: Nao
A7: PA | B7: Nao
A8: PI | B8: Nao
A9: RO | B9: Nao
A10: RR | B10: Nao
A11: TO | B11: Nao
A13: =COUNTA(A2:A11) -> 10

Sheet ICMS
B2: Regiao | C2: UF | D2: ICMS | E2: tem GN
B3: CO | C3: DF | E3: =_xlfn.XLOOKUP(C3,'uf sem GN'!A:A,'uf sem GN'!B:B,"Sim") -> Nao
B4: CO | C4: GO | E4: =_xlfn.XLOOKUP(C4,'uf sem GN'!A:A,'uf sem GN'!B:B,"Sim") -> Nao
B5: N | C5: AC | E5: =_xlfn.XLOOKUP(C5,'uf sem GN'!A:A,'uf sem GN'!B:B,"Sim") -> Nao
B6: N | C6: AP | E6: =_xlfn.XLOOKUP(C6,'uf sem GN'!A:A,'uf sem GN'!B:B,"Sim") -> Nao
B7: N | C7: PA | E7: =_xlfn.XLOOKUP(C7,'uf sem GN'!A:A,'uf sem GN'!B:B,"Sim") -> Nao
B8: N | C8: RO | E8: =_xlfn.XLOOKUP(C8,'uf sem GN'!A:A,'uf sem GN'!B:B,"Sim") -> Nao
B9: N | C9: RR | E9: =_xlfn.XLOOKUP(C9,'uf sem GN'!A:A,'uf sem GN'!B:B,"Sim") -> Nao
B10: N | C10: TO | E10: =_xlfn.XLOOKUP(C10,'uf sem GN'!A:A,'uf sem GN'!B:B,"Sim") -> Nao
B11: NE | C11: MA | E11: =_xlfn.XLOOKUP(C11,'uf sem GN'!A:A,'uf sem GN'!B:B,"Sim") -> Nao
B12: NE | C12: PI | E12: =_xlfn.XLOOKUP(C12,'uf sem GN'!A:A,'uf sem GN'!B:B,"Sim") -> Nao
B13: CO | C13: MT | D13: 0.17 | E13: =_xlfn.XLOOKUP(C13,'uf sem GN'!A:A,'uf sem GN'!B:B,"Sim") -> Sim
B14: CO | C14: MS | D14: 0.17 | E14: =_xlfn.XLOOKUP(C14,'uf sem GN'!A:A,'uf sem GN'!B:B,"Sim") -> Sim
B15: N | C15: AM | D15: 0.2 | E15: =_xlfn.XLOOKUP(C15,'uf sem GN'!A:A,'uf sem GN'!B:B,"Sim") -> Sim
B16: NE | C16: AL | D16: 0.2 | E16: =_xlfn.XLOOKUP(C16,'uf sem GN'!A:A,'uf sem GN'!B:B,"Sim") -> Sim
B17: NE | C17: BA | D17: 0.12 | E17: =_xlfn.XLOOKUP(C17,'uf sem GN'!A:A,'uf sem GN'!B:B,"Sim") -> Sim
B18: NE | C18: CE | D18: 0.2 | E18: =_xlfn.XLOOKUP(C18,'uf sem GN'!A:A,'uf sem GN'!B:B,"Sim") -> Sim
B19: NE | C19: PB | D19: 0.2 | E19: =_xlfn.XLOOKUP(C19,'uf sem GN'!A:A,'uf sem GN'!B:B,"Sim") -> Sim
B20: NE | C20: PE | D20: 0.205 | E20: =_xlfn.XLOOKUP(C20,'uf sem GN'!A:A,'uf sem GN'!B:B,"Sim") -> Sim
B21: NE | C21: RN | D21: 0.2 | E21: =_xlfn.XLOOKUP(C21,'uf sem GN'!A:A,'uf sem GN'!B:B,"Sim") -> Sim
B22: NE | C22: SE | D22: 0.2 | E22: =_xlfn.XLOOKUP(C22,'uf sem GN'!A:A,'uf sem GN'!B:B,"Sim") -> Sim
B23: S | C23: PR | D23: 0.12 | E23: =_xlfn.XLOOKUP(C23,'uf sem GN'!A:A,'uf sem GN'!B:B,"Sim") -> Sim
B24: S | C24: RS | D24: 0.12 | E24: =_xlfn.XLOOKUP(C24,'uf sem GN'!A:A,'uf sem GN'!B:B,"Sim") -> Sim
... B29: SE | C29: SP | D29: 0.15 | E29: =_xlfn.XLOOKUP(C29,'uf sem GN'!A:A,'uf sem GN'!B:B,"Sim") -> Sim

Sheet Observações
B2: Naturgy SP | C2: Faixa media Condominio estimada VQ
B3: PB | C3: Semana para mês (*4,345)
C5: Algumas tarifas estao publicadas por dia ou semana
C6: Há estados com incentivos fiscais

Sheet conversa_com_o_tributario
C2: industria pode creditar 1,47 a cada kg de glp | D2: Simples não
C3: Industria pode creditar 9,25% de PIS/COFINS sobre o faturado da nota | D3: Lucro Real
C5: Tem haver com a aplicação
C10: Nota | D10: valor unit | E10: Valor total
C11: 60kg glp | D11: 7 | E11: =D11*60 -> 420
C14: Uso no processo industrial, pode creditar creditos GN e GLP
C15: exceto o Industrial não credita
C17: Regime de trbutação
C18: Uso do GLP do cliente
C20: pf não credita
C21: pj com inscricão estatual pode creditar
C22: em 01/01/2027 morre pis/cofins
C23: icms 2029 gradativo

Sheet Cliente_teste_metrica
B2: Cliente_teste | D2: kg glp | E2: preço por kg glp | F2: m3 GN | G2: preço por m3 GN | H2: preço equivalente gn kg glp
B3: 11642 | D3: 11642 | E3: 6.73 | F3: =D3*1.25 -> 14552.5 | G3: 3.01 | H3: =G3*1.25 -> 3.7625
C4: fatura | E4: =D3*E3 -> 78350.66 | G4: =F3*G3 -> 43803.025 | H4: =D3*H3 -> 43803.025
H7: =E3-H3 -> 2.9675
